oilele/__init__.py
oilele/_version.py
oilele/oilala.py
oilele/okivy.py
oilele/lib/__init__.py
oilele/lib/logging_utils.py
oilele/lib/parse_args.py
oilele/screen/__init__.py
oilele/screen/comic_screen.py
oilele/screen/comic_screen_chafa.py
oilele/screen/comic_screen_inky.py
oilele/screen/comic_screen_pygame.py
Oilele-1.0.1.dist-info/LICENSE
Oilele-1.0.1.dist-info/METADATA
Oilele-1.0.1.dist-info/WHEEL
Oilele-1.0.1.dist-info/entry_points.txt
Oilele-1.0.1.dist-info/top_level.txt
Oilele-1.0.1.dist-info/RECORD
