Metadata-Version: 2.1
Name: Oilele
Version: 1.0.1
Summary: Comic book visualizer
Home-page: https://github.com/canepan/Oilele
Author: Nicola Canepa
Author-email: canne74@gmail.com
Classifier: Development Status :: 5 - Production/Stable
Classifier: Intended Audience :: Developers
Classifier: License :: OSI Approved :: MIT License
Classifier: Programming Language :: Python :: 3
Classifier: Programming Language :: Python :: 3 :: Only
Requires-Python: >=3.8
License-File: LICENSE
Requires-Dist: attrs (>=17.4.0)
Requires-Dist: pdf2image
Requires-Dist: pygame
Provides-Extra: docs
Requires-Dist: sphinx (>=3.5) ; extra == 'docs'
Requires-Dist: jaraco.packaging (>=9) ; extra == 'docs'
Requires-Dist: rst.linker (>=1.9) ; extra == 'docs'
Requires-Dist: furo ; extra == 'docs'
Provides-Extra: rar
Requires-Dist: unrar ; extra == 'rar'
Provides-Extra: rpi
Requires-Dist: inky ; extra == 'rpi'
Requires-Dist: numpy ; extra == 'rpi'
Requires-Dist: RPi.GPIO ; extra == 'rpi'
Provides-Extra: testing
Requires-Dist: pytest (>=6) ; extra == 'testing'
Requires-Dist: pytest-checkdocs (>=2.4) ; extra == 'testing'
Requires-Dist: pytest-flake8 ; extra == 'testing'
Requires-Dist: flake8 (<5) ; extra == 'testing'
Requires-Dist: pytest-cov ; extra == 'testing'
Requires-Dist: pytest-enabler (>=1.3) ; extra == 'testing'
Requires-Dist: pytest-black (>=0.3.7) ; (platform_python_implementation != "PyPy") and extra == 'testing'
Requires-Dist: pytest-mypy (>=0.9.1) ; (platform_python_implementation != "PyPy") and extra == 'testing'
